{
	"metadata": {
		"version": 4.4,
		"type": "Object",
		"generator": "Object3D.toJSON"
	},
	"geometries": [
		{
			"uuid": "5EBAB172-E3D9-40D5-ABDE-B5ABC1DF2381",
			"type": "BoxBufferGeometry",
			"width": 1,
			"height": 1,
			"depth": 1
		},
		{
			"uuid": "CD848C07-BE81-4594-B3EB-F65A8DF6DB7A",
			"type": "CylinderBufferGeometry",
			"radiusTop": 1,
			"radiusBottom": 1,
			"height": 2,
			"radialSegments": 32,
			"heightSegments": 1,
			"openEnded": false
		}],
	"materials": [
		{
			"uuid": "2AD6B199-FF37-4FAA-89B7-5DE4CF6423BA",
			"type": "MeshStandardMaterial",
			"color": 8421504,
			"roughness": 0.5,
			"metalness": 0.54,
			"emissive": 0,
			"depthFunc": 3,
			"depthTest": true,
			"depthWrite": true,
			"skinning": false,
			"morphTargets": false
		},
		{
			"uuid": "2837F9F2-1C34-4F58-9BF0-F94AA3B69E66",
			"type": "MeshStandardMaterial",
			"color": 16777215,
			"roughness": 0.5,
			"metalness": 0.5,
			"emissive": 0,
			"depthFunc": 3,
			"depthTest": true,
			"depthWrite": true,
			"skinning": false,
			"morphTargets": false
		},
		{
			"uuid": "21A7E151-ABA8-4A9D-AF28-7DD68535487A",
			"type": "MeshStandardMaterial",
			"color": 255,
			"roughness": 0.5,
			"metalness": 0.5,
			"emissive": 0,
			"depthFunc": 3,
			"depthTest": true,
			"depthWrite": true,
			"skinning": false,
			"morphTargets": false
		}],
	"object": {
		"uuid": "202DACD9-17A8-4FF9-8F6F-BEB89C310F64",
		"type": "Group",
		"name": "Group 8",
		"matrix": [1,0,0,0,0,1,0,0,0,0,1,0,0,0,0,1],
		"children": [
			{
				"uuid": "E34D08A6-3246-48BC-99C6-CD24D89F3361",
				"type": "Mesh",
				"name": "Box 6",
				"matrix": [0.203326,0,0,0,0,1,0,0,0,0,1,0,-0.25,0,0,1],
				"geometry": "5EBAB172-E3D9-40D5-ABDE-B5ABC1DF2381",
				"material": "2AD6B199-FF37-4FAA-89B7-5DE4CF6423BA"
			},
			{
				"uuid": "3242C185-E536-4899-ACF4-225DCF289B47",
				"type": "Mesh",
				"name": "Cylinder 7",
				"matrix": [0,0.1,0,0,-0.2,0,0,0,0,0,0.1,0,-0.549282,0,0,1],
				"geometry": "CD848C07-BE81-4594-B3EB-F65A8DF6DB7A",
				"material": "2837F9F2-1C34-4F58-9BF0-F94AA3B69E66"
			},
			{
				"uuid": "51CD6347-28DF-49C5-9BA4-33EBCF30AB6F",
				"type": "Mesh",
				"name": "Cylinder 7",
				"matrix": [0,0.1,0,0,-0.2,0,0,0,0,0,0.1,0,0.556852,0,0,1],
				"geometry": "CD848C07-BE81-4594-B3EB-F65A8DF6DB7A",
				"material": "2837F9F2-1C34-4F58-9BF0-F94AA3B69E66"
			},
			{
				"uuid": "FBFB504D-6B26-4E90-894D-D3BCBE1DDF6F",
				"type": "DirectionalLight",
				"name": "DirectionalLight 3",
				"matrix": [1,0,0,0,0,1,0,0,0,0,1,0,5,10,7.5,1],
				"color": 16777215,
				"intensity": 1,
				"shadow": {
					"camera": {
						"uuid": "745FB5B2-AA83-430B-ABA2-6F96ADDE5B08",
						"type": "OrthographicCamera",
						"zoom": 1,
						"left": -5,
						"right": 5,
						"top": 5,
						"bottom": -5,
						"near": 0.5,
						"far": 500
					}
				}
			},
			{
				"uuid": "3DD7A7F5-36DC-4B93-A737-7DFBF82C9F6A",
				"type": "AmbientLight",
				"name": "AmbientLight 2",
				"matrix": [1,0,0,0,0,1,0,0,0,0,1,0,0,0,0,1],
				"color": 2236962,
				"intensity": 1
			},
			{
				"uuid": "8D6ACE99-6614-4D55-8736-32859F204AB1",
				"type": "Mesh",
				"name": "Box 6",
				"matrix": [0.303168,0,0,0,0,1,0,0,0,0,1,0,0,0,0,1],
				"geometry": "5EBAB172-E3D9-40D5-ABDE-B5ABC1DF2381",
				"material": "21A7E151-ABA8-4A9D-AF28-7DD68535487A"
			},
			{
				"uuid": "D7B89947-6D1C-454F-B791-399FBA8AC4D2",
				"type": "Mesh",
				"name": "Box 6",
				"matrix": [0.203326,0,0,0,0,1,0,0,0,0,1,0,0.252859,0,0,1],
				"geometry": "5EBAB172-E3D9-40D5-ABDE-B5ABC1DF2381",
				"material": "2AD6B199-FF37-4FAA-89B7-5DE4CF6423BA"
			}]
	}
}